{
  "allow": [
    {
      "id": "4c16",
      "headers": {
        "Content-Type": "application/json"
      },
      "data": "1234"
    },
    {
      "id": "8cdf",
      "headers": {
        "Content-Type": "application/json"
      },
      "data": "1234"
    },
    {
      "id": "ba2f",
      "headers": {
        "Content-Type": "application/json"
      },
      "data": "1234"
    },
    {
      "id": "3846",
      "username": "1234",
      "phone": "1234",
      "code": "1234",
      "password": "1234"
    },
    {
      "id": "5217",
      "username": "1234",
      "phone": "1234",
      "code": "1234",
      "password": "1234"
    },
    {
      "id": "129b",
      "username": "1234",
      "phone": "1234",
      "code": "1234",
      "password": "1234"
    },
    {
      "id": "f6c9",
      "username": "1234",
      "phone": "1234",
      "code": "1234",
      "password": "1234"
    },
    {
      "id": "fa98",
      "username": "1234",
      "phone": "01088313956",
      "code": "123456qq",
      "password": "1234"
    },
    {
      "id": "7993",
      "username": "hnk1112",
      "phone": "01088313956",
      "code": "12345",
      "password": "1234qwer"
    },
    {
      "id": "0906",
      "username": "qqqqq",
      "phone": "01088313956",
      "code": "12345",
      "password": "tjdnjswns112"
    },
    {
      "id": "8e3f",
      "username": "qqqqq",
      "phone": "01088313956",
      "code": "12345",
      "password": "tjdnjswns112"
    },
    {
      "id": "ab39",
      "username": "qqqqq",
      "phone": "01088313956",
      "code": "12345",
      "password": "tjdnjswns112"
    },
    {
      "id": "114a",
      "username": "qqqqq",
      "phone": "01088313956",
      "code": "12345",
      "password": "tjdnjswns112"
    },
    {
      "id": "0e3d",
      "username": "qqqqq",
      "phone": "01088313956",
      "code": "12345",
      "password": "tjdnjswns112"
    },
    {
      "id": "664f",
      "username": "qqqqq",
      "phone": "01088313956",
      "code": "12345",
      "password": "tjdnjswns112"
    },
    {
      "id": "8058",
      "username": "qqqqq",
      "phone": "01088313956",
      "code": "12345",
      "password": "tjdnjswns112"
    },
    {
      "id": "abb4",
      "username": "qqqqq",
      "phone": "01088313956",
      "code": "12345",
      "password": "tjdnjswns112"
    },
    {
      "id": "5ee8",
      "username": "qqqqq",
      "phone": "01088313956",
      "code": "12345",
      "password": "tjdnjswns112"
    },
    {
      "id": "5151",
      "username": "qqqqq",
      "phone": "01088313956",
      "code": "12345",
      "password": "tjdnjswns112"
    },
    {
      "id": "d733",
      "username": "qqqqq",
      "phone": "01088313956",
      "code": "12345",
      "password": "tjdnjswns112"
    },
    {
      "id": "05fe",
      "username": "qqqqq",
      "phone": "01088313956",
      "code": "12345",
      "password": "tjdnjswns112"
    },
    {
      "id": "9046",
      "username": "qqqqq",
      "phone": "01088313956",
      "code": "12345",
      "password": "tjdnjswns112"
    },
    {
      "id": "a17a",
      "username": "qqqqq",
      "phone": "01088313956",
      "code": "12345",
      "password": "tjdnjswns112"
    },
    {
      "id": "959f",
      "username": "qqqqq",
      "phone": "01088313956",
      "code": "12345",
      "password": "tjdnjswns112"
    }
  ],
  "phone": [
    {
      "id": "0880",
      "phone": "1234"
    },
    {
      "id": "8a45",
      "phone": ""
    },
    {
      "id": "e54e",
      "phone": ""
    },
    {
      "id": "5eae"
    },
    {
      "id": "9360"
    },
    {
      "id": "3d9f"
    },
    {
      "id": "b342"
    },
    {
      "id": "5175"
    },
    {
      "id": "4983"
    },
    {
      "id": "deb5"
    },
    {
      "id": "0cc8"
    },
    {
      "id": "d6fc"
    },
    {
      "id": "e9b1"
    },
    {
      "id": "8b07"
    },
    {
      "id": "6835"
    },
    {
      "id": "d72c",
      "phone": "01088313956"
    },
    {
      "id": "9985",
      "phone": "01088313956"
    },
    {
      "id": "e159",
      "phone": "01088313956"
    },
    {
      "id": "3e49",
      "phone": "01088313956"
    },
    {
      "id": "6ab5",
      "phone": "01088313956"
    },
    {
      "id": "0d89",
      "phone": "01088313956"
    },
    {
      "id": "d1c8",
      "phone": "01088313956"
    },
    {
      "id": "7f22",
      "phone": "01088313956"
    }
  ],
  "code": [
    {
      "id": "fb58",
      "code": "1234"
    },
    {
      "id": "73e3",
      "code": "12345"
    },
    {
      "id": "4a0f",
      "code": "12345"
    },
    {
      "id": "815f",
      "code": "12345"
    },
    {
      "id": "0617",
      "code": "12345"
    },
    {
      "id": "32b8",
      "code": "12345"
    },
    {
      "id": "60ba",
      "code": "12345"
    },
    {
      "id": "a58a",
      "code": "12345"
    },
    {
      "id": "7d80",
      "code": "12345"
    },
    {
      "id": "4963",
      "code": "12345"
    },
    {
      "id": "9971",
      "code": "12345"
    },
    {
      "id": "8ea8",
      "code": "12345"
    }
  ]
}